htestp/__about__.py
htestp/__init__.py
htestp-0.0.2.dist-info/METADATA
htestp-0.0.2.dist-info/WHEEL
htestp-0.0.2.dist-info/licenses/LICENSE.txt
htestp-0.0.2.dist-info/RECORD
